AUTHORS
LICENSE.txt
MANIFEST.in
README.md
setup.py
pysodium/__init__.py
pysodium.egg-info/PKG-INFO
pysodium.egg-info/SOURCES.txt
pysodium.egg-info/dependency_links.txt
pysodium.egg-info/top_level.txt
test/__init__.py
test/test_pysodium.py