Metadata-Version: 2.1
Name: pysodium
Version: 0.7.13
Summary: python libsodium wrapper
Home-page: https://github.com/stef/pysodium
Author: Stefan Marsiske
Author-email: s@ctrlc.hu
License: BSD
Keywords: cryptography API NaCl libsodium
Classifier: Development Status :: 4 - Beta
Classifier: License :: OSI Approved :: BSD License
Classifier: Topic :: Security :: Cryptography
Classifier: Topic :: Security
Requires: libsodium
License-File: LICENSE.txt
License-File: AUTHORS
